k8s_voca/__init__.py
k8s_voca/k8s_voca.py
k8s_voca-0.3.0.dist-info/LICENSE
k8s_voca-0.3.0.dist-info/METADATA
k8s_voca-0.3.0.dist-info/WHEEL
k8s_voca-0.3.0.dist-info/entry_points.txt
k8s_voca-0.3.0.dist-info/top_level.txt
k8s_voca-0.3.0.dist-info/RECORD
