Metadata-Version: 2.1
Name: k8s-voca
Version: 0.3.0
Summary: kubernetes vocabulary
Home-page: https://dmario24.github.io/k8s-voca
Author: dmario24
Author-email: data.mario24@gmail.com
License: GNU General Public License (GPL)
Project-URL: Bug Tracker, https://github.com/dmario24/k8s-voca/issues
Platform: macOS
Classifier: Programming Language :: Python :: 3
Classifier: License :: OSI Approved :: GNU General Public License (GPL)
Classifier: Operating System :: OS Independent
Requires-Python: >=3.6
License-File: LICENSE
